Banking/__init__.py
Banking/main.py
Banking/test_account.py
Banking/test_action.py
Banking/test_suite.py
Banking/test_transaction.py
Banking/test_viewandaction.py
Banking/admin/__init__.py
Banking/admin/action.py
Banking/admin/card.py
Banking/admin/store.py
Banking/admin/view.py
Banking/user/__init__.py
Banking/user/account.py
Banking/user/transaction.py
banking633-0.0.5.dist-info/LICENSE.txt
banking633-0.0.5.dist-info/METADATA
banking633-0.0.5.dist-info/WHEEL
banking633-0.0.5.dist-info/top_level.txt
banking633-0.0.5.dist-info/RECORD
